autocam/__init__.py
autocam/__main__.py
autocam/_version.py
autocam/py.typed
autocam-1.1.3.dist-info/LICENSE
autocam-1.1.3.dist-info/METADATA
autocam-1.1.3.dist-info/WHEEL
autocam-1.1.3.dist-info/entry_points.txt
autocam-1.1.3.dist-info/RECORD
