Metadata-Version: 2.3
Name: autocam
Version: 1.1.3
Summary: Autocam
License: MIT
Author: Petrus H Zwart
Author-email: phzwart@lbl.gov
Requires-Python: >=3.9,<4.0
Classifier: Development Status :: 3 - Alpha
Classifier: License :: OSI Approved :: MIT License
Classifier: Programming Language :: Python :: 3
Classifier: Programming Language :: Python :: 3.9
Classifier: Programming Language :: Python :: 3.10
Classifier: Programming Language :: Python :: 3.11
Classifier: Programming Language :: Python :: 3.12
Classifier: Programming Language :: Python :: 3.13
Requires-Dist: click (>=8.0.1)
Requires-Dist: wheel (>=0.38.1)
Project-URL: Changelog, https://github.com/phzwart/autocam/releases
Project-URL: Documentation, https://autocam.readthedocs.io
Project-URL: Homepage, https://github.com/phzwart/autocam
Project-URL: Repository, https://github.com/phzwart/autocam
